ares_testbed_cli-1.0.2.data/scripts/otbctl_directory.sh
otbctl/__init__.py
otbctl/__main__.py
otbctl/github_service.py
otbctl/log_management.py
otbctl/otbctl_main.py
otbctl/otbctl_mock.py
otbctl/otbctl_server.py
otbctl/yaml_validate.py
ares_testbed_cli-1.0.2.dist-info/METADATA
ares_testbed_cli-1.0.2.dist-info/WHEEL
ares_testbed_cli-1.0.2.dist-info/entry_points.txt
ares_testbed_cli-1.0.2.dist-info/top_level.txt
ares_testbed_cli-1.0.2.dist-info/RECORD
