Metadata-Version: 2.1
Name: ares-testbed-cli
Version: 1.0.2
Home-page: https://github.optum.com/ecp/optum-testbed-cli
Author: Venkata Krishna Lolla
Author-email: venkata.lolla@optum.com
Maintainer: Venkata Krishna Lolla
Requires-Dist: python-dotenv
Requires-Dist: requests
Requires-Dist: pyyaml
Requires-Dist: tabulate
Requires-Dist: numpy
Requires-Dist: munch
Requires-Dist: validators
Requires-Dist: pygithub
Requires-Dist: schema
